pyutilator/__init__.py
pyutilator/print/__init__.py
pyutilator/print/print_args.py
pyutilator/print/print_kwargs.py
pyutilator/print/print_return_value.py
pyutilator/timing/__init__.py
pyutilator/timing/measure_time.py
pyutilator-1.0.0.dist-info/LICENSE.md
pyutilator-1.0.0.dist-info/METADATA
pyutilator-1.0.0.dist-info/WHEEL
pyutilator-1.0.0.dist-info/top_level.txt
pyutilator-1.0.0.dist-info/RECORD
