Metadata-Version: 2.1
Name: pyutilator
Version: 1.0.0
Summary: Python Utility Decorators
Home-page: https://github.com/antoprince001/pyutilator
Author: Antony Prince J
Author-email: antoprince001@gmail.com
Classifier: Programming Language :: Python :: 3
Classifier: License :: OSI Approved :: MIT License
Classifier: Operating System :: OS Independent
Requires-Python: >=3.6
License-File: LICENSE.md
